{
  "region": "광주_전라권",
  "contentType": "쇼핑",
  "contentTypeId": 38,
  "total": 38,
  "items": [
    {
      "addr1": "전남광주통합특별시 서구 매월2로 16",
      "addr2": "(매월동)",
      "areacode": "5",
      "cat1": "A04",
      "cat2": "A0401",
      "cat3": "A04010200",
      "contentid": "2783783",
      "contenttypeid": "38",
      "createdtime": "20211130225947",
      "firstimage": "http://tong.visitkorea.or.kr/cms/resource/21/3528421_image2_1.jpg",
      "firstimage2": "http://tong.visitkorea.or.kr/cms/resource/21/3528421_image3_1.jpg",
      "cpyrhtDivCd": "Type1",
      "mapx": "126.8586608367",
      "mapy": "35.1161856771",
      "mlevel": "6",
      "modifiedtime": "20260630212627",
      "sigungucode": "5",
      "tel": "",
      "title": "서부농수산물도매시장",
      "zipcode": "62072",
      "lDongRegnCd": "12",
      "lDongSignguCd": "240",
      "lclsSystm1": "SH",
      "lclsSystm2": "SH06",
      "lclsSystm3": "SH060200"
    },
    {
      "addr1": "전남광주통합특별시 광산구 비아중앙로 26-1",
      "addr2": "(비아동)",
      "areacode": "5",
      "cat1": "A04",
      "cat2": "A0401",
      "cat3": "A04010100",
      "contentid": "2783789",
      "contenttypeid": "38",
      "createdtime": "20211130230435",
      "firstimage": "http://tong.visitkorea.or.kr/cms/resource/60/3528360_image2_1.jpg",
      "firstimage2": "http://tong.visitkorea.or.kr/cms/resource/60/3528360_image3_1.jpg",
      "cpyrhtDivCd": "Type1",
      "mapx": "126.8252806044",
      "mapy": "35.2213982286",
      "mlevel": "6",
      "modifiedtime": "20260630212627",
      "sigungucode": "1",
      "tel": "",
      "title": "비아5일시장",
      "zipcode": "62240",
      "lDongRegnCd": "12",
      "lDongSignguCd": "330",
      "lclsSystm1": "SH",
      "lclsSystm2": "SH06",
      "lclsSystm3": "SH060100"
    },
    {
      "addr1": "전남광주통합특별시 동구 중앙로196번길 15-6 (궁동)",
      "addr2": "",
      "areacode": "5",
      "cat1": "A04",
      "cat2": "A0401",
      "cat3": "A04010700",
      "contentid": "1621202",
      "contenttypeid": "38",
      "createdtime": "20120503185809",
      "firstimage": "http://tong.visitkorea.or.kr/cms/resource/65/1587565_image2_1.jpg",
      "firstimage2": "http://tong.visitkorea.or.kr/cms/resource/65/1587565_image3_1.jpg",
      "cpyrhtDivCd": "Type3",
      "mapx": "126.9176242274",
      "mapy": "35.1498495384",
      "mlevel": "6",
      "modifiedtime": "20260630184428",
      "sigungucode": "3",
      "tel": "",
      "title": "무안요(광주)",
      "zipcode": "61475",
      "lDongRegnCd": "12",
      "lDongSignguCd": "210",
      "lclsSystm1": "SH",
      "lclsSystm2": "SH05",
      "lclsSystm3": "SH050100"
    },
    {
      "addr1": "전남광주통합특별시 서구 마륵벽진길 23",
      "addr2": "(마륵동)",
      "areacode": "5",
      "cat1": "A04",
      "cat2": "A0401",
      "cat3": "A04010600",
      "contentid": "2765207",
      "contenttypeid": "38",
      "createdtime": "20211101182838",
      "firstimage": "http://tong.visitkorea.or.kr/cms/resource/27/3528427_image2_1.jpg",
      "firstimage2": "http://tong.visitkorea.or.kr/cms/resource/27/3528427_image3_1.jpg",
      "cpyrhtDivCd": "Type1",
      "mapx": "126.8455168899",
      "mapy": "35.1428074499",
      "mlevel": "6",
      "modifiedtime": "20260630184428",
      "sigungucode": "5",
      "tel": "",
      "title": "상무화훼단지",
      "zipcode": "61999",
      "lDongRegnCd": "12",
      "lDongSignguCd": "240",
      "lclsSystm1": "SH",
      "lclsSystm2": "SH05",
      "lclsSystm3": "SH050200"
    },
    {
      "addr1": "전남광주통합특별시 광산구 사암로 300 (월곡동)",
      "addr2": "",
      "areacode": "5",
      "cat1": "A04",
      "cat2": "A0401",
      "cat3": "A04010200",
      "contentid": "2783776",
      "contenttypeid": "38",
      "createdtime": "20211130225523",
      "firstimage": "http://tong.visitkorea.or.kr/cms/resource/69/3551369_image2_1.jpg",
      "firstimage2": "http://tong.visitkorea.or.kr/cms/resource/69/3551369_image3_1.jpg",
      "cpyrhtDivCd": "Type1",
      "mapx": "126.8096610164",
      "mapy": "35.1713258469",
      "mlevel": "6",
      "modifiedtime": "20260630184428",
      "sigungucode": "1",
      "tel": "",
      "title": "월곡시장",
      "zipcode": "62347",
      "lDongRegnCd": "12",
      "lDongSignguCd": "330",
      "lclsSystm1": "SH",
      "lclsSystm2": "SH06",
      "lclsSystm3": "SH060200"
    },
    {
      "addr1": "전남광주통합특별시 담양군 창평면 사동길 14-25",
      "addr2": "(창평면)",
      "areacode": "38",
      "cat1": "A04",
      "cat2": "A0401",
      "cat3": "A04010100",
      "contentid": "132062",
      "contenttypeid": "38",
      "createdtime": "20021118090000",
      "firstimage": "http://tong.visitkorea.or.kr/cms/resource/88/1972088_image2_1.jpg",
      "firstimage2": "http://tong.visitkorea.or.kr/cms/resource/88/1972088_image3_1.jpg",
      "cpyrhtDivCd": "Type3",
      "mapx": "127.0298226417",
      "mapy": "35.3694988367",
      "mlevel": "6",
      "modifiedtime": "20260630212627",
      "sigungucode": "7",
      "tel": "",
      "title": "창평장 (5, 10일)",
      "zipcode": "57389",
      "lDongRegnCd": "12",
      "lDongSignguCd": "710",
      "lclsSystm1": "SH",
      "lclsSystm2": "SH06",
      "lclsSystm3": "SH060100"
    },
    {
      "addr1": "전남광주통합특별시 담양군 대전면 대치8길 28-12",
      "addr2": "",
      "areacode": "38",
      "cat1": "A04",
      "cat2": "A0401",
      "cat3": "A04010100",
      "contentid": "132061",
      "contenttypeid": "38",
      "createdtime": "20021118090000",
      "firstimage": "http://tong.visitkorea.or.kr/cms/resource/45/3582045_image2_1.jpg",
      "firstimage2": "http://tong.visitkorea.or.kr/cms/resource/45/3582045_image3_1.jpg",
      "cpyrhtDivCd": "Type1",
      "mapx": "126.8861071953",
      "mapy": "35.2754209258",
      "mlevel": "6",
      "modifiedtime": "20260630184428",
      "sigungucode": "7",
      "tel": "",
      "title": "대치장 (3, 8일)",
      "zipcode": "57328",
      "lDongRegnCd": "12",
      "lDongSignguCd": "710",
      "lclsSystm1": "SH",
      "lclsSystm2": "SH06",
      "lclsSystm3": "SH060100"
    },
    {
      "addr1": "전남광주통합특별시 나주시 풍물시장2길 12-14 (이창동)",
      "addr2": "",
      "areacode": "38",
      "cat1": "A04",
      "cat2": "A0401",
      "cat3": "A04010100",
      "contentid": "132166",
      "contenttypeid": "38",
      "createdtime": "20020418090000",
      "firstimage": "http://tong.visitkorea.or.kr/cms/resource/36/1972036_image2_1.jpg",
      "firstimage2": "http://tong.visitkorea.or.kr/cms/resource/36/1972036_image3_1.jpg",
      "cpyrhtDivCd": "Type3",
      "mapx": "126.7078383684",
      "mapy": "34.9915055499",
      "mlevel": "6",
      "modifiedtime": "20260630212627",
      "sigungucode": "6",
      "tel": "",
      "title": "영산포풍물시장(5, 10일)",
      "zipcode": "58274",
      "lDongRegnCd": "12",
      "lDongSignguCd": "170",
      "lclsSystm1": "SH",
      "lclsSystm2": "SH06",
      "lclsSystm3": "SH060100"
    },
    {
      "addr1": "전남광주통합특별시 나주시 남평읍 지석로 21",
      "addr2": "",
      "areacode": "38",
      "cat1": "A04",
      "cat2": "A0401",
      "cat3": "A04010100",
      "contentid": "132167",
      "contenttypeid": "38",
      "createdtime": "20020423090000",
      "firstimage": "",
      "firstimage2": "",
      "cpyrhtDivCd": "",
      "mapx": "126.8405197515",
      "mapy": "35.0456544424",
      "mlevel": "6",
      "modifiedtime": "20260630212627",
      "sigungucode": "6",
      "tel": "",
      "title": "남평장 (1, 6일)",
      "zipcode": "58227",
      "lDongRegnCd": "12",
      "lDongSignguCd": "170",
      "lclsSystm1": "SH",
      "lclsSystm2": "SH06",
      "lclsSystm3": "SH060100"
    },
    {
      "addr1": "전남광주통합특별시 나주시 공산면 금강로 253",
      "addr2": "",
      "areacode": "38",
      "cat1": "A04",
      "cat2": "A0401",
      "cat3": "A04010700",
      "contentid": "132466",
      "contenttypeid": "38",
      "createdtime": "20020411090000",
      "firstimage": "http://tong.visitkorea.or.kr/cms/resource/57/3537357_image2_1.jpeg",
      "firstimage2": "http://tong.visitkorea.or.kr/cms/resource/57/3537357_image3_1.jpeg",
      "cpyrhtDivCd": "Type3",
      "mapx": "126.5908633152",
      "mapy": "34.9622124632",
      "mlevel": "6",
      "modifiedtime": "20260630212627",
      "sigungucode": "6",
      "tel": "",
      "title": "충주산방",
      "zipcode": "58289",
      "lDongRegnCd": "12",
      "lDongSignguCd": "170",
      "lclsSystm1": "SH",
      "lclsSystm2": "SH05",
      "lclsSystm3": "SH050100"
    },
    {
      "addr1": "전남광주통합특별시 나주시 공산면 공산로 120",
      "addr2": "(공산면)",
      "areacode": "38",
      "cat1": "A04",
      "cat2": "A0401",
      "cat3": "A04010100",
      "contentid": "132059",
      "contenttypeid": "38",
      "createdtime": "20020417090000",
      "firstimage": "http://tong.visitkorea.or.kr/cms/resource/64/1971564_image2_1.jpg",
      "firstimage2": "http://tong.visitkorea.or.kr/cms/resource/64/1971564_image3_1.jpg",
      "cpyrhtDivCd": "Type3",
      "mapx": "126.6091093957",
      "mapy": "34.9429566034",
      "mlevel": "6",
      "modifiedtime": "20260630184428",
      "sigungucode": "6",
      "tel": "",
      "title": "공산장 (1, 6일)",
      "zipcode": "58290",
      "lDongRegnCd": "12",
      "lDongSignguCd": "170",
      "lclsSystm1": "SH",
      "lclsSystm2": "SH06",
      "lclsSystm3": "SH060100"
    },
    {
      "addr1": "전남광주통합특별시 나주시 청동길 14 (삼도동)",
      "addr2": "",
      "areacode": "38",
      "cat1": "A04",
      "cat2": "A0401",
      "cat3": "A04010200",
      "contentid": "1976875",
      "contenttypeid": "38",
      "createdtime": "20141217222418",
      "firstimage": "http://tong.visitkorea.or.kr/cms/resource/84/3548284_image2_1.jpg",
      "firstimage2": "http://tong.visitkorea.or.kr/cms/resource/84/3548284_image3_1.jpg",
      "cpyrhtDivCd": "Type1",
      "mapx": "126.7235497464",
      "mapy": "35.0370340097",
      "mlevel": "6",
      "modifiedtime": "20260630184428",
      "sigungucode": "6",
      "tel": "",
      "title": "나주목사고을시장",
      "zipcode": "58252",
      "lDongRegnCd": "12",
      "lDongSignguCd": "170",
      "lclsSystm1": "SH",
      "lclsSystm2": "SH06",
      "lclsSystm3": "SH060200"
    },
    {
      "addr1": "전남광주통합특별시 화순군 능주면 학포로 1955",
      "addr2": "",
      "areacode": "38",
      "cat1": "A04",
      "cat2": "A0401",
      "cat3": "A04010100",
      "contentid": "132093",
      "contenttypeid": "38",
      "createdtime": "20040227090000",
      "firstimage": "http://tong.visitkorea.or.kr/cms/resource/64/3536164_image2_1.jpg",
      "firstimage2": "http://tong.visitkorea.or.kr/cms/resource/64/3536164_image3_1.jpg",
      "cpyrhtDivCd": "Type1",
      "mapx": "126.9597716980",
      "mapy": "34.9909292860",
      "mlevel": "6",
      "modifiedtime": "20260630212627",
      "sigungucode": "24",
      "tel": "",
      "title": "능주전통시장",
      "zipcode": "58153",
      "lDongRegnCd": "12",
      "lDongSignguCd": "760",
      "lclsSystm1": "SH",
      "lclsSystm2": "SH06",
      "lclsSystm3": "SH060100"
    },
    {
      "addr1": "전남광주통합특별시 화순군 화순읍 시장길 44",
      "addr2": "",
      "areacode": "38",
      "cat1": "A04",
      "cat2": "A0401",
      "cat3": "A04010100",
      "contentid": "132098",
      "contenttypeid": "38",
      "createdtime": "20040227090000",
      "firstimage": "http://tong.visitkorea.or.kr/cms/resource/74/3536174_image2_1.jpg",
      "firstimage2": "http://tong.visitkorea.or.kr/cms/resource/74/3536174_image3_1.jpg",
      "cpyrhtDivCd": "Type1",
      "mapx": "126.9832290254",
      "mapy": "35.0596108299",
      "mlevel": "6",
      "modifiedtime": "20260630184428",
      "sigungucode": "24",
      "tel": "",
      "title": "화순고인돌전통시장",
      "zipcode": "58122",
      "lDongRegnCd": "12",
      "lDongSignguCd": "760",
      "lclsSystm1": "SH",
      "lclsSystm2": "SH06",
      "lclsSystm3": "SH060100"
    },
    {
      "addr1": "전남광주통합특별시 장성군 삼월길 5  ",
      "addr2": "",
      "areacode": "38",
      "cat1": "A04",
      "cat2": "A0401",
      "cat3": "A04010100",
      "contentid": "2926899",
      "contenttypeid": "38",
      "createdtime": "20221201154253",
      "firstimage": "http://tong.visitkorea.or.kr/cms/resource/62/3582462_image2_1.jpg",
      "firstimage2": "http://tong.visitkorea.or.kr/cms/resource/62/3582462_image3_1.jpg",
      "cpyrhtDivCd": "Type1",
      "mapx": "126.7741583797",
      "mapy": "35.2913727847",
      "mlevel": "6",
      "modifiedtime": "20260630184428",
      "sigungucode": "19",
      "tel": "",
      "title": "황룡시장",
      "zipcode": "57227",
      "lDongRegnCd": "12",
      "lDongSignguCd": "840",
      "lclsSystm1": "SH",
      "lclsSystm2": "SH06",
      "lclsSystm3": "SH060100"
    },
    {
      "addr1": "전남광주통합특별시 여수시 광무동",
      "addr2": "",
      "areacode": "38",
      "cat1": "A04",
      "cat2": "A0401",
      "cat3": "A04010100",
      "contentid": "132069",
      "contenttypeid": "38",
      "createdtime": "20021204090000",
      "firstimage": "http://tong.visitkorea.or.kr/cms/resource/67/3580367_image2_1.jpg",
      "firstimage2": "http://tong.visitkorea.or.kr/cms/resource/67/3580367_image3_1.jpg",
      "cpyrhtDivCd": "Type1",
      "mapx": "127.7281966158",
      "mapy": "34.7407955187",
      "mlevel": "6",
      "modifiedtime": "20260630184428",
      "sigungucode": "13",
      "tel": "",
      "title": "서시장 (4, 9일)",
      "zipcode": "59718",
      "lDongRegnCd": "12",
      "lDongSignguCd": "130",
      "lclsSystm1": "SH",
      "lclsSystm2": "SH06",
      "lclsSystm3": "SH060100"
    },
    {
      "addr1": "전남광주통합특별시 여수시 소라면 하세동길 12-2",
      "addr2": "",
      "areacode": "38",
      "cat1": "A04",
      "cat2": "A0401",
      "cat3": "A04010100",
      "contentid": "132070",
      "contenttypeid": "38",
      "createdtime": "20021204090000",
      "firstimage": "http://tong.visitkorea.or.kr/cms/resource/99/3580299_image2_1.jpg",
      "firstimage2": "http://tong.visitkorea.or.kr/cms/resource/99/3580299_image3_1.jpg",
      "cpyrhtDivCd": "Type1",
      "mapx": "127.6320285789",
      "mapy": "34.7979985577",
      "mlevel": "6",
      "modifiedtime": "20260630184428",
      "sigungucode": "13",
      "tel": "",
      "title": "덕양시장",
      "zipcode": "59649",
      "lDongRegnCd": "12",
      "lDongSignguCd": "130",
      "lclsSystm1": "SH",
      "lclsSystm2": "SH06",
      "lclsSystm3": "SH060100"
    },
    {
      "addr1": "전남광주통합특별시 여수시 오동도로 238-32 오동도 등대 ",
      "addr2": "",
      "areacode": "38",
      "cat1": "A04",
      "cat2": "A0401",
      "cat3": "A04010900",
      "contentid": "1343107",
      "contenttypeid": "38",
      "createdtime": "20110728004615",
      "firstimage": "",
      "firstimage2": "",
      "cpyrhtDivCd": "",
      "mapx": "127.7676180755",
      "mapy": "34.7444819002",
      "mlevel": "6",
      "modifiedtime": "20260630184428",
      "sigungucode": "13",
      "tel": "",
      "title": "동박새꿈정원",
      "zipcode": "59723",
      "lDongRegnCd": "12",
      "lDongSignguCd": "130",
      "lclsSystm1": "SH",
      "lclsSystm2": "SH05",
      "lclsSystm3": "SH050300"
    },
    {
      "addr1": "전남광주통합특별시 여수시 어항단지로 205 (봉산동)",
      "addr2": "",
      "areacode": "38",
      "cat1": "A04",
      "cat2": "A0401",
      "cat3": "A04010900",
      "contentid": "1343398",
      "contenttypeid": "38",
      "createdtime": "20110728011423",
      "firstimage": "http://tong.visitkorea.or.kr/cms/resource/22/3027322_image2_1.jpg",
      "firstimage2": "http://tong.visitkorea.or.kr/cms/resource/22/3027322_image3_1.jpg",
      "cpyrhtDivCd": "Type3",
      "mapx": "127.7280468858",
      "mapy": "34.7307160898",
      "mlevel": "6",
      "modifiedtime": "20260630184428",
      "sigungucode": "13",
      "tel": "",
      "title": "여수 특산품전시판매장",
      "zipcode": "59764",
      "lDongRegnCd": "12",
      "lDongSignguCd": "130",
      "lclsSystm1": "SH",
      "lclsSystm2": "SH05",
      "lclsSystm3": "SH050300"
    },
    {
      "addr1": "전남광주통합특별시 여수시 무선중앙로 43 (선원동)",
      "addr2": "",
      "areacode": "38",
      "cat1": "A04",
      "cat2": "A0401",
      "cat3": "A04010600",
      "contentid": "2755850",
      "contenttypeid": "38",
      "createdtime": "20211013012818",
      "firstimage": "http://tong.visitkorea.or.kr/cms/resource/09/3582109_image2_1.jpg",
      "firstimage2": "http://tong.visitkorea.or.kr/cms/resource/09/3582109_image3_1.jpg",
      "cpyrhtDivCd": "Type1",
      "mapx": "127.6495248838",
      "mapy": "34.7737876842",
      "mlevel": "6",
      "modifiedtime": "20260630184428",
      "sigungucode": "13",
      "tel": "",
      "title": "중앙쇼핑센터",
      "zipcode": "59640",
      "lDongRegnCd": "12",
      "lDongSignguCd": "130",
      "lclsSystm1": "SH",
      "lclsSystm2": "SH05",
      "lclsSystm3": "SH050200"
    },
    {
      "addr1": "전남광주통합특별시 여수시 여객선터미널길 24",
      "addr2": "(교동)",
      "areacode": "38",
      "cat1": "A04",
      "cat2": "A0401",
      "cat3": "A04010200",
      "contentid": "2783118",
      "contenttypeid": "38",
      "createdtime": "20211130005545",
      "firstimage": "http://tong.visitkorea.or.kr/cms/resource/06/2787606_image2_1.jpg",
      "firstimage2": "http://tong.visitkorea.or.kr/cms/resource/06/2787606_image2_1.jpg",
      "cpyrhtDivCd": "Type3",
      "mapx": "127.7317935902",
      "mapy": "34.7381847622",
      "mlevel": "6",
      "modifiedtime": "20260630184428",
      "sigungucode": "13",
      "tel": "",
      "title": "여수수산시장",
      "zipcode": "59735",
      "lDongRegnCd": "12",
      "lDongSignguCd": "130",
      "lclsSystm1": "SH",
      "lclsSystm2": "SH06",
      "lclsSystm3": "SH060200"
    },
    {
      "addr1": "전남광주통합특별시 여수시 돌산읍 향일암로 57",
      "addr2": "",
      "areacode": "38",
      "cat1": "A04",
      "cat2": "A0401",
      "cat3": "A04010600",
      "contentid": "3010413",
      "contenttypeid": "38",
      "createdtime": "20230913145534",
      "firstimage": "http://tong.visitkorea.or.kr/cms/resource/83/3010383_image2_1.jpg",
      "firstimage2": "http://tong.visitkorea.or.kr/cms/resource/83/3010383_image3_1.jpg",
      "cpyrhtDivCd": "Type3",
      "mapx": "127.8026854999",
      "mapy": "34.5939771211",
      "mlevel": "6",
      "modifiedtime": "20260630184428",
      "sigungucode": "13",
      "tel": "",
      "title": "김미영 돌산갓김치",
      "zipcode": "59778",
      "lDongRegnCd": "12",
      "lDongSignguCd": "130",
      "lclsSystm1": "SH",
      "lclsSystm2": "SH05",
      "lclsSystm3": "SH050200"
    },
    {
      "addr1": "전남광주통합특별시 해남군 해남읍 중앙2로 100-1",
      "addr2": "",
      "areacode": "38",
      "cat1": "A04",
      "cat2": "A0401",
      "cat3": "A04010100",
      "contentid": "132275",
      "contenttypeid": "38",
      "createdtime": "20020424090000",
      "firstimage": "http://tong.visitkorea.or.kr/cms/resource/04/1972104_image2_1.jpg",
      "firstimage2": "http://tong.visitkorea.or.kr/cms/resource/04/1972104_image3_1.jpg",
      "cpyrhtDivCd": "Type3",
      "mapx": "126.5960446344",
      "mapy": "34.5680874430",
      "mlevel": "6",
      "modifiedtime": "20260630212627",
      "sigungucode": "23",
      "tel": "",
      "title": "해남장 (1, 6일)",
      "zipcode": "59041",
      "lDongRegnCd": "12",
      "lDongSignguCd": "790",
      "lclsSystm1": "SH",
      "lclsSystm2": "SH06",
      "lclsSystm3": "SH060100"
    },
    {
      "addr1": "전남광주통합특별시 해남군 북평면 달량진길 52-10",
      "addr2": "",
      "areacode": "38",
      "cat1": "A04",
      "cat2": "A0401",
      "cat3": "A04010100",
      "contentid": "132092",
      "contenttypeid": "38",
      "createdtime": "20020417090000",
      "firstimage": "",
      "firstimage2": "",
      "cpyrhtDivCd": "",
      "mapx": "126.6270624955",
      "mapy": "34.4042535393",
      "mlevel": "6",
      "modifiedtime": "20260630184428",
      "sigungucode": "23",
      "tel": "",
      "title": "남창장 (2, 7일)",
      "zipcode": "59055",
      "lDongRegnCd": "12",
      "lDongSignguCd": "790",
      "lclsSystm1": "SH",
      "lclsSystm2": "SH06",
      "lclsSystm3": "SH060100"
    },
    {
      "addr1": "전남광주통합특별시 진도군 진도읍 조금시장길 25",
      "addr2": "",
      "areacode": "38",
      "cat1": "A04",
      "cat2": "A0401",
      "cat3": "A04010100",
      "contentid": "132090",
      "contenttypeid": "38",
      "createdtime": "20030416090000",
      "firstimage": "http://tong.visitkorea.or.kr/cms/resource/39/3061039_image2_1.jpg",
      "firstimage2": "http://tong.visitkorea.or.kr/cms/resource/39/3061039_image3_1.jpg",
      "cpyrhtDivCd": "Type3",
      "mapx": "126.2573042985",
      "mapy": "34.4812305613",
      "mlevel": "6",
      "modifiedtime": "20260630184428",
      "sigungucode": "21",
      "tel": "",
      "title": "진도장·진도조금시장 (2, 7일)",
      "zipcode": "58922",
      "lDongRegnCd": "12",
      "lDongSignguCd": "860",
      "lclsSystm1": "SH",
      "lclsSystm2": "SH06",
      "lclsSystm3": "SH060100"
    },
    {
      "addr1": "전남광주통합특별시 순천시 별량면 일출길 141",
      "addr2": "",
      "areacode": "38",
      "cat1": "A04",
      "cat2": "A0401",
      "cat3": "A04010700",
      "contentid": "1342639",
      "contenttypeid": "38",
      "createdtime": "20110727021740",
      "firstimage": "",
      "firstimage2": "",
      "cpyrhtDivCd": "",
      "mapx": "127.4832092713",
      "mapy": "34.8688824839",
      "mlevel": "6",
      "modifiedtime": "20260630184428",
      "sigungucode": "11",
      "tel": "",
      "title": "태랑도예원",
      "zipcode": "58030",
      "lDongRegnCd": "12",
      "lDongSignguCd": "150",
      "lclsSystm1": "SH",
      "lclsSystm2": "SH05",
      "lclsSystm3": "SH050100"
    },
    {
      "addr1": "전남광주통합특별시 순천시 북문길 40 (동외동)",
      "addr2": "",
      "areacode": "38",
      "cat1": "A04",
      "cat2": "A0401",
      "cat3": "A04010200",
      "contentid": "3505810",
      "contenttypeid": "38",
      "createdtime": "20250714133421",
      "firstimage": "",
      "firstimage2": "",
      "cpyrhtDivCd": "",
      "mapx": "127.4849124008",
      "mapy": "34.9586141000",
      "mlevel": "6",
      "modifiedtime": "20260630184428",
      "sigungucode": "11",
      "tel": "",
      "title": "순천 웃장",
      "zipcode": "57939",
      "lDongRegnCd": "12",
      "lDongSignguCd": "150",
      "lclsSystm1": "SH",
      "lclsSystm2": "SH06",
      "lclsSystm3": "SH060200"
    },
    {
      "addr1": "전북특별자치도 전주시 덕진구 동부대로 1185 (송천동2가)",
      "addr2": "",
      "areacode": "37",
      "cat1": "A04",
      "cat2": "A0401",
      "cat3": "A04010200",
      "contentid": "2750890",
      "contenttypeid": "38",
      "createdtime": "20210929001106",
      "firstimage": "http://tong.visitkorea.or.kr/cms/resource/14/3585714_image2_1.jpg",
      "firstimage2": "http://tong.visitkorea.or.kr/cms/resource/14/3585714_image3_1.jpg",
      "cpyrhtDivCd": "Type1",
      "mapx": "127.1174380954",
      "mapy": "35.8681937388",
      "mlevel": "6",
      "modifiedtime": "20251217161942",
      "sigungucode": "12",
      "tel": "",
      "title": "전주시 농수산물도매시장",
      "zipcode": "54827",
      "lDongRegnCd": "52",
      "lDongSignguCd": "113",
      "lclsSystm1": "SH",
      "lclsSystm2": "SH06",
      "lclsSystm3": "SH060200"
    },
    {
      "addr1": "전북특별자치도 전주시 완산구 전주천서로 141 (동완산동)",
      "addr2": "",
      "areacode": "37",
      "cat1": "A04",
      "cat2": "A0401",
      "cat3": "A04010200",
      "contentid": "3065483",
      "contenttypeid": "38",
      "createdtime": "20231211144707",
      "firstimage": "http://tong.visitkorea.or.kr/cms/resource/74/3065474_image2_1.jpg",
      "firstimage2": "http://tong.visitkorea.or.kr/cms/resource/74/3065474_image3_1.jpg",
      "cpyrhtDivCd": "Type3",
      "mapx": "127.1460592583",
      "mapy": "35.8113062644",
      "mlevel": "6",
      "modifiedtime": "20250801152313",
      "sigungucode": "12",
      "tel": "",
      "title": "전주 도깨비 시장",
      "zipcode": "55098",
      "lDongRegnCd": "52",
      "lDongSignguCd": "111",
      "lclsSystm1": "SH",
      "lclsSystm2": "SH06",
      "lclsSystm3": "SH060200"
    },
    {
      "addr1": "전북특별자치도 전주시 덕진구 모래내4길 8-8 (인후동2가)",
      "addr2": "",
      "areacode": "37",
      "cat1": "A04",
      "cat2": "A0401",
      "cat3": "A04010200",
      "contentid": "1187336",
      "contenttypeid": "38",
      "createdtime": "20110127193250",
      "firstimage": "http://tong.visitkorea.or.kr/cms/resource/57/3064157_image2_1.jpg",
      "firstimage2": "http://tong.visitkorea.or.kr/cms/resource/57/3064157_image3_1.jpg",
      "cpyrhtDivCd": "Type3",
      "mapx": "127.1438866461",
      "mapy": "35.8336092448",
      "mlevel": "6",
      "modifiedtime": "20250801143704",
      "sigungucode": "12",
      "tel": "",
      "title": "전주 모래내시장",
      "zipcode": "54926",
      "lDongRegnCd": "52",
      "lDongSignguCd": "113",
      "lclsSystm1": "SH",
      "lclsSystm2": "SH06",
      "lclsSystm3": "SH060200"
    },
    {
      "addr1": "전북특별자치도 전주시 완산구 은행로 96-1 (교동)",
      "addr2": "",
      "areacode": "37",
      "cat1": "A04",
      "cat2": "A0401",
      "cat3": "A04010900",
      "contentid": "3066402",
      "contenttypeid": "38",
      "createdtime": "20231212111001",
      "firstimage": "http://tong.visitkorea.or.kr/cms/resource/84/3066384_image2_1.jpg",
      "firstimage2": "http://tong.visitkorea.or.kr/cms/resource/84/3066384_image3_1.jpg",
      "cpyrhtDivCd": "Type3",
      "mapx": "127.1529364199",
      "mapy": "35.8114702540",
      "mlevel": "6",
      "modifiedtime": "20250729113301",
      "sigungucode": "12",
      "tel": "",
      "title": "전북특별자치도 관광기념품 100선 판매관",
      "zipcode": "55044",
      "lDongRegnCd": "52",
      "lDongSignguCd": "111",
      "lclsSystm1": "SH",
      "lclsSystm2": "SH05",
      "lclsSystm3": "SH050300"
    },
    {
      "addr1": "전북특별자치도 전주시 완산구 풍남문1길 19-3",
      "addr2": "",
      "areacode": "37",
      "cat1": "A04",
      "cat2": "A0401",
      "cat3": "A04010200",
      "contentid": "132326",
      "contenttypeid": "38",
      "createdtime": "20031119090000",
      "firstimage": "http://tong.visitkorea.or.kr/cms/resource/35/3428535_image2_1.jpg",
      "firstimage2": "http://tong.visitkorea.or.kr/cms/resource/35/3428535_image3_1.jpg",
      "cpyrhtDivCd": "Type3",
      "mapx": "127.1475535303",
      "mapy": "35.8128283393",
      "mlevel": "6",
      "modifiedtime": "20250711094139",
      "sigungucode": "12",
      "tel": "",
      "title": "전주 남부시장",
      "zipcode": "55043",
      "lDongRegnCd": "52",
      "lDongSignguCd": "111",
      "lclsSystm1": "SH",
      "lclsSystm2": "SH06",
      "lclsSystm3": "SH060200"
    },
    {
      "addr1": "전북특별자치도 남원시 봉당길 8 (동충동)",
      "addr2": "",
      "areacode": "37",
      "cat1": "A04",
      "cat2": "A0401",
      "cat3": "A04010200",
      "contentid": "132769",
      "contenttypeid": "38",
      "createdtime": "20070420090000",
      "firstimage": "http://tong.visitkorea.or.kr/cms/resource/66/3536266_image2_1.jpg",
      "firstimage2": "http://tong.visitkorea.or.kr/cms/resource/66/3536266_image3_1.jpg",
      "cpyrhtDivCd": "Type1",
      "mapx": "127.3835208152",
      "mapy": "35.4118556896",
      "mlevel": "6",
      "modifiedtime": "20250918135010",
      "sigungucode": "4",
      "tel": "",
      "title": "남원 터미널시장",
      "zipcode": "55749",
      "lDongRegnCd": "52",
      "lDongSignguCd": "190",
      "lclsSystm1": "SH",
      "lclsSystm2": "SH06",
      "lclsSystm3": "SH060200"
    },
    {
      "addr1": "전북특별자치도 남원시 의총로 51 (금동)",
      "addr2": "",
      "areacode": "37",
      "cat1": "A04",
      "cat2": "A0401",
      "cat3": "A04010200",
      "contentid": "2755020",
      "contenttypeid": "38",
      "createdtime": "20211008200537",
      "firstimage": "http://tong.visitkorea.or.kr/cms/resource/98/2755098_image2_1.jpg",
      "firstimage2": "http://tong.visitkorea.or.kr/cms/resource/98/2755098_image3_1.jpg",
      "cpyrhtDivCd": "Type3",
      "mapx": "127.3758522306",
      "mapy": "35.4048285735",
      "mlevel": "6",
      "modifiedtime": "20250905095248",
      "sigungucode": "4",
      "tel": "",
      "title": "춘향골 공설시장",
      "zipcode": "55768",
      "lDongRegnCd": "52",
      "lDongSignguCd": "190",
      "lclsSystm1": "SH",
      "lclsSystm2": "SH06",
      "lclsSystm3": "SH060200"
    },
    {
      "addr1": "전북특별자치도 남원시 인월면 인월로 65-3",
      "addr2": "",
      "areacode": "37",
      "cat1": "A04",
      "cat2": "A0401",
      "cat3": "A04010100",
      "contentid": "132305",
      "contenttypeid": "38",
      "createdtime": "20020418090000",
      "firstimage": "http://tong.visitkorea.or.kr/cms/resource/95/3516995_image2_1.jpg",
      "firstimage2": "http://tong.visitkorea.or.kr/cms/resource/95/3516995_image3_1.jpg",
      "cpyrhtDivCd": "Type3",
      "mapx": "127.6021057660",
      "mapy": "35.4615261085",
      "mlevel": "6",
      "modifiedtime": "20250805143143",
      "sigungucode": "4",
      "tel": "",
      "title": "남원인월시장",
      "zipcode": "55715",
      "lDongRegnCd": "52",
      "lDongSignguCd": "190",
      "lclsSystm1": "SH",
      "lclsSystm2": "SH06",
      "lclsSystm3": "SH060100"
    },
    {
      "addr1": "전북특별자치도 남원시 요천로 1357 (조산동)",
      "addr2": "",
      "areacode": "37",
      "cat1": "A04",
      "cat2": "A0401",
      "cat3": "A04010700",
      "contentid": "132464",
      "contenttypeid": "38",
      "createdtime": "20040216090000",
      "firstimage": "http://tong.visitkorea.or.kr/cms/resource/98/3064298_image2_1.jpg",
      "firstimage2": "http://tong.visitkorea.or.kr/cms/resource/98/3064298_image3_1.jpg",
      "cpyrhtDivCd": "Type3",
      "mapx": "127.3718555359",
      "mapy": "35.3980792677",
      "mlevel": "6",
      "modifiedtime": "20250804145103",
      "sigungucode": "4",
      "tel": "",
      "title": "남원 목기공예사",
      "zipcode": "55766",
      "lDongRegnCd": "52",
      "lDongSignguCd": "190",
      "lclsSystm1": "SH",
      "lclsSystm2": "SH05",
      "lclsSystm3": "SH050100"
    },
    {
      "addr1": "전북특별자치도 남원시 의총로 51",
      "addr2": "",
      "areacode": "37",
      "cat1": "A04",
      "cat2": "A0401",
      "cat3": "A04010100",
      "contentid": "132043",
      "contenttypeid": "38",
      "createdtime": "20050114090000",
      "firstimage": "http://tong.visitkorea.or.kr/cms/resource/51/3068151_image2_1.jpg",
      "firstimage2": "http://tong.visitkorea.or.kr/cms/resource/51/3068151_image3_1.jpg",
      "cpyrhtDivCd": "Type3",
      "mapx": "127.3758938988",
      "mapy": "35.4046035997",
      "mlevel": "6",
      "modifiedtime": "20250804133307",
      "sigungucode": "4",
      "tel": "",
      "title": "남원장 / 남원공설시장 (4, 9일)",
      "zipcode": "55768",
      "lDongRegnCd": "52",
      "lDongSignguCd": "190",
      "lclsSystm1": "SH",
      "lclsSystm2": "SH06",
      "lclsSystm3": "SH060100"
    },
    {
      "addr1": "전북특별자치도 남원시 주천면 장백산로 10",
      "addr2": "",
      "areacode": "37",
      "cat1": "A04",
      "cat2": "A0401",
      "cat3": "A04010900",
      "contentid": "3357428",
      "contenttypeid": "38",
      "createdtime": "20240902110056",
      "firstimage": "http://tong.visitkorea.or.kr/cms/resource/46/3357446_image2_1.jpg",
      "firstimage2": "http://tong.visitkorea.or.kr/cms/resource/46/3357446_image3_1.jpg",
      "cpyrhtDivCd": "Type3",
      "mapx": "127.4487405659",
      "mapy": "35.3920479512",
      "mlevel": "6",
      "modifiedtime": "20240902132559",
      "sigungucode": "4",
      "tel": "",
      "title": "지리산맑은물춘향골 영농조합법인",
      "zipcode": "55802",
      "lDongRegnCd": "52",
      "lDongSignguCd": "190",
      "lclsSystm1": "SH",
      "lclsSystm2": "SH05",
      "lclsSystm3": "SH050300"
    }
  ]
}